LICENSE
MANIFEST.in
README.md
requirements.txt
setup.py
slackclient_cli/__init__.py
slackclient_cli/__version__.txt
slackclient_cli/api_specific.py
slackclient_cli/cli.py
slackclient_cli.egg-info/PKG-INFO
slackclient_cli.egg-info/SOURCES.txt
slackclient_cli.egg-info/dependency_links.txt
slackclient_cli.egg-info/entry_points.txt
slackclient_cli.egg-info/requires.txt
slackclient_cli.egg-info/top_level.txt