Metadata-Version: 1.1
Name: slackclient-cli
Version: 0.4.4
Summary: A command line interface for Slack
Home-page: https://github.com/Yoshiyuki-Nakahara/python-slackclient-cli
Author: Yoshiyuki-Nakahara
Author-email: president.hanage@gmail.com
License: MIT
Keywords: slack api cli
Platform: UNKNOWN
Classifier: Development Status :: 5 - Production/Stable
Classifier: License :: OSI Approved :: MIT License
Classifier: Programming Language :: Python :: 2.7
